[
    {
        "name":"osman",
        "phoneNumber":"555555555",
        "point":"30",
        "message":"Lorem ipsum dolor sit amet consectetur adipisicing elit. Accusamus sunt nostrum accusantium beataeff"
    }, {
        "name":"osman",
        "phoneNumber":"555555555",
        "point":"-5.8",
        "message":"Lorem ipsum dolor sit amet consectetur adipisicing elit. Accusamus sunt nostrum accusantium beataeff"
    }, {
        "name":"osman",
        "phoneNumber":"555555555",
        "point":"-2",
        "message":"Lorem ipsum dolor sit amet consectetur adipisicing elit. Accusamus sunt nostrum accusantium beataeff"
    }, {
        "name":"osman",
        "phoneNumber":"555555555",
        "point":"7.3",
        "message":"Lorem ipsum dolor sit amet consectetur adipisicing elit. Accusamus sunt nostrum accusantium beataeff"
    }, {
        "name":"osman",
        "phoneNumber":"555555555",
        "point":"5",
        "message":"Lorem ipsum dolor sit amet consectetur adipisicing elit. Accusamus sunt nostrum accusantium beataeff"
    }, {
        "name":"osman",
        "phoneNumber":"555555555",
        "point":"5",
        "message":"Lorem ipsum dolor sit amet consectetur adipisicing elit. Accusamus sunt nostrum accusantium beataeff"
    }, {
        "name":"osman",
        "phoneNumber":"555555555",
        "point":"15",
        "message":"Lorem ipsum dolor sit amet consectetur adipisicing elit. Accusamus sunt nostrum accusantium beataeff"
    }, {
        "name":"osman",
        "phoneNumber":"555555555",
        "point":"5",
        "message":"Lorem ipsum dolor sit amet consectetur adipisicing elit. Accusamus sunt nostrum accusantium beataeff"
    }, {
        "name":"osman",
        "phoneNumber":"555555555",
        "point":"5",
        "message":"Lorem ipsum dolor sit amet consectetur adipisicing elit. Accusamus sunt nostrum accusantium beataeff"
    }, {
        "name":"sevcan",
        "phoneNumber":"555555555",
        "point":"9.8",
        "message":"Lorem ipsum dolor sit amet consectetur adipisicing elit. Accusamus sunt nostrum accusantium beataeff"
    }
]